referit/__init__.py
referit/refer.py
referit/evaluation/__init__.py
referit/evaluation/ref_evaluation.py
referit/evaluation/bleu/__init__.py
referit/evaluation/bleu/bleu.py
referit/evaluation/bleu/bleu_scorer.py
referit/evaluation/cider/__init__.py
referit/evaluation/cider/cider.py
referit/evaluation/cider/cider_scorer.py
referit/evaluation/meteor/__init__.py
referit/evaluation/meteor/meteor.py
referit/evaluation/rouge/__init__.py
referit/evaluation/rouge/rouge.py
referit/evaluation/tokenizer/__init__.py
referit/evaluation/tokenizer/ptbtokenizer.py
referit/external/__init__.py
referit/external/_mask.c
referit/external/_mask.cpython-36m-x86_64-linux-gnu.so
referit/external/mask.py
referit/external/maskApi.c
referit-1.0.0.dist-info/DESCRIPTION.rst
referit-1.0.0.dist-info/METADATA
referit-1.0.0.dist-info/RECORD
referit-1.0.0.dist-info/WHEEL
referit-1.0.0.dist-info/metadata.json
referit-1.0.0.dist-info/top_level.txt
