Metadata-Version: 2.0
Name: referit
Version: 1.0.0
Summary: Python wrapper to load the ReferIt Game dataset
Home-page: https://github.com/lichengunc/refer
Author: Licheng Yu
Author-email: licheng@cs.unc.edu
License: MIT
Keywords: referit,segmentation,dataset
Platform: UNKNOWN
Classifier: Development Status :: 4 - Beta
Classifier: Intended Audience :: Developers
Classifier: Intended Audience :: Science/Research
Classifier: License :: OSI Approved :: MIT License
Classifier: Operating System :: MacOS
Classifier: Operating System :: Microsoft :: Windows
Classifier: Operating System :: POSIX :: Linux
Classifier: Programming Language :: Python :: 2.7
Classifier: Programming Language :: Python :: 3.5
Classifier: Programming Language :: Python :: 3.6
Requires-Dist: cython
Requires-Dist: matplotlib
Requires-Dist: numpy
Requires-Dist: scikit-image
